multiprocess_kafka_consumer/__init__.py
multiprocess_kafka_consumer/multiprocess_kafka_consumer.py
multiprocess_kafka_consumer-0.1.14.dist-info/METADATA
multiprocess_kafka_consumer-0.1.14.dist-info/WHEEL
multiprocess_kafka_consumer-0.1.14.dist-info/top_level.txt
multiprocess_kafka_consumer-0.1.14.dist-info/RECORD
