Metadata-Version: 2.1
Name: multiprocess-kafka-consumer
Version: 0.1.14
Summary: UNKNOWN
Home-page: UNKNOWN
Author: UNKNOWN
Author-email: UNKNOWN
License: UNKNOWN
Platform: UNKNOWN
Requires-Dist: kafka-python
Requires-Dist: requests
Requires-Dist: schedule
